tfr_image/__init__.py
tfr_image/tfr_image.py
tfr_image/utils.py
tfr_image-1.2.dist-info/LICENSE
tfr_image-1.2.dist-info/METADATA
tfr_image-1.2.dist-info/WHEEL
tfr_image-1.2.dist-info/top_level.txt
tfr_image-1.2.dist-info/RECORD
