Metadata-Version: 2.1
Name: tfr-image
Version: 1.2
Summary: TFRimage is minimal tool to create TFRecords from a small dataset of images
Home-page: https://github.com/jmarrietar/tfr_image
License: MIT
Platform: UNKNOWN
